asyncio_run_in_process/__init__.py
asyncio_run_in_process/_child.py
asyncio_run_in_process/_child_trio.py
asyncio_run_in_process/_utils.py
asyncio_run_in_process/abc.py
asyncio_run_in_process/constants.py
asyncio_run_in_process/exceptions.py
asyncio_run_in_process/main.py
asyncio_run_in_process/process.py
asyncio_run_in_process/state.py
asyncio_run_in_process/typing.py
asyncio_run_in_process/typing_compat.py
asyncio_run_in_process/tools/__init__.py
asyncio_run_in_process/tools/sleep.py
asyncio_run_in_process-0.1.0a10.dist-info/LICENSE
asyncio_run_in_process-0.1.0a10.dist-info/METADATA
asyncio_run_in_process-0.1.0a10.dist-info/WHEEL
asyncio_run_in_process-0.1.0a10.dist-info/top_level.txt
asyncio_run_in_process-0.1.0a10.dist-info/RECORD
