Metadata-Version: 2.1
Name: asyncio-run-in-process
Version: 0.1.0a10
Summary: asyncio-run-in-process: Asyncio friendly replacement for multiprocessing
Home-page: https://github.com/ethereum/asyncio-run-in-process
Author: The Ethereum Foundation
Author-email: snakecharmers@ethereum.org
License: MIT
Keywords: ethereum
Platform: UNKNOWN
Classifier: Development Status :: 3 - Alpha
Classifier: Intended Audience :: Developers
Classifier: License :: OSI Approved :: MIT License
Classifier: Natural Language :: English
Classifier: Programming Language :: Python :: 3
Classifier: Programming Language :: Python :: 3.6
Classifier: Programming Language :: Python :: 3.7
Classifier: Programming Language :: Python :: Implementation :: PyPy
Requires-Python: >=3.6, <4
Requires-Dist: async-generator (<2,>=1.10)
Requires-Dist: cloudpickle (<2,>=1.2.1)
Requires-Dist: trio-typing (<0.6,>=0.5.0)
Requires-Dist: trio (<0.17,>=0.16)
Provides-Extra: dev
Requires-Dist: Sphinx (<2,>=1.6.5) ; extra == 'dev'
Requires-Dist: async-exit-stack (==1.0.1) ; extra == 'dev'
Requires-Dist: bumpversion (<1,>=0.5.3) ; extra == 'dev'
Requires-Dist: flake8 (==3.7.9) ; extra == 'dev'
Requires-Dist: ipython ; extra == 'dev'
Requires-Dist: isort (<5,>=4.2.15) ; extra == 'dev'
Requires-Dist: mypy (==0.770) ; extra == 'dev'
Requires-Dist: pydocstyle (<4,>=3.0.0) ; extra == 'dev'
Requires-Dist: pytest-asyncio (==0.10.0) ; extra == 'dev'
Requires-Dist: pytest-watch (<5,>=4.1.0) ; extra == 'dev'
Requires-Dist: pytest-xdist ; extra == 'dev'
Requires-Dist: pytest (==5.2.2) ; extra == 'dev'
Requires-Dist: sphinx-rtd-theme (>=0.1.9) ; extra == 'dev'
Requires-Dist: tox (<3,>=2.9.1) ; extra == 'dev'
Requires-Dist: twine ; extra == 'dev'
Requires-Dist: wheel ; extra == 'dev'
Requires-Dist: typing-extensions (<4,>=3.7.4.1) ; (python_version < "3.8") and extra == 'dev'
Provides-Extra: doc
Requires-Dist: Sphinx (<2,>=1.6.5) ; extra == 'doc'
Requires-Dist: sphinx-rtd-theme (>=0.1.9) ; extra == 'doc'
Provides-Extra: lint
Requires-Dist: flake8 (==3.7.9) ; extra == 'lint'
Requires-Dist: isort (<5,>=4.2.15) ; extra == 'lint'
Requires-Dist: mypy (==0.770) ; extra == 'lint'
Requires-Dist: pydocstyle (<4,>=3.0.0) ; extra == 'lint'
Requires-Dist: typing-extensions (<4,>=3.7.4.1) ; (python_version < "3.8") and extra == 'lint'
Provides-Extra: test
Requires-Dist: async-exit-stack (==1.0.1) ; extra == 'test'
Requires-Dist: pytest-asyncio (==0.10.0) ; extra == 'test'
Requires-Dist: pytest-xdist ; extra == 'test'
Requires-Dist: pytest (==5.2.2) ; extra == 'test'
Requires-Dist: tox (<3,>=2.9.1) ; extra == 'test'
